[
  {
    "youtube_url": "https://youtu.be/hDtLWJApJDQ?si=-oC80nLIbQ15hK3T",
    "custom_name": null,
    "pipeline_start": "2025-09-02 17:11:10",
    "schema_version": "2.0",
    "processing_version": "v2.1",
    "stages": {
      "subtitles": {
        "status": "success",
        "duration": 2.0276918411254883,
        "json_path": "data\\raw_subtitles\\hDtLWJApJDQ.json",
        "srt_path": "data\\raw_subtitles\\hDtLWJApJDQ.srt",
        "txt_path": "data\\raw_subtitles\\hDtLWJApJDQ.txt"
      },
      "text_processing": {
        "status": "success",
        "duration": 99.25517106056213,
        "sag_v2_output": "data\\sag_final\\hDtLWJApJDQ.for_vector.json",
        "review_markdown": "data\\sag_final\\hDtLWJApJDQ.for_review.md",
        "blocks_created": 4,
        "schema_version": "2.0"
      },
      "pipeline_complete": {
        "status": "success",
        "duration": 0.0
      }
    },
    "status": "success",
    "total_duration": 101.28412914276123,
    "pipeline_end": "2025-09-02 17:12:51",
    "final_outputs": {
      "sag_v2_json": "data\\sag_final\\hDtLWJApJDQ.for_vector.json",
      "review_markdown": "data\\sag_final\\hDtLWJApJDQ.for_review.md"
    }
  }
]